tomly/__init__.py
tomly/_version.py
tomly-0.1.4.dist-info/METADATA
tomly-0.1.4.dist-info/WHEEL
tomly-0.1.4.dist-info/licenses/LICENSE
tomly-0.1.4.dist-info/RECORD
